{"type":"FeatureCollection","features":[{"type":"Feature","geometry":{"type":"Point","coordinates":[8.19120707100851,48.789499214077]},"properties":{"stop_id":"de:08211:1847:2:31","stop_name":"Baden-Baden Bahnhof","zone_id":"0480","stop_url":"","location_type":null,"parent_station":"Parent1847","agency_key":"kvv","agency_name":"VBK GmbH","routes":[{"route_id":"11-201-C-s17-2","route_short_name":"201 (BBL)","route_long_name":""},{"route_id":"11-201-C-s17-5","route_short_name":"201 (BBL)","route_long_name":""},{"route_id":"11-205-C-s17-3","route_short_name":"205 (BBL)","route_long_name":""},{"route_id":"11-205-C-s17-5","route_short_name":"205 (BBL)","route_long_name":""},{"route_id":"11-207-C-s17-4","route_short_name":"207 (BBL)","route_long_name":""},{"route_id":"11-207-C-s17-6","route_short_name":"207 (BBL)","route_long_name":""},{"route_id":"11-216-C-s17-3","route_short_name":"216 (BBL)","route_long_name":""},{"route_id":"11-218-C-s17-2","route_short_name":"218 (BBL)","route_long_name":""},{"route_id":"11-218-C-s17-3","route_short_name":"218 (BBL)","route_long_name":""},{"route_id":"11-243-C-s17-2","route_short_name":"243 (BBL)","route_long_name":""},{"route_id":"11-285-C-s17-1","route_short_name":"285 (BBL)","route_long_name":""},{"route_id":"40-71-1-s17-1","route_short_name":"SEV S71 (AVG)","route_long_name":""},{"route_id":"40-71-E-s17-6","route_short_name":"SEV 71 (AVG)","route_long_name":""},{"route_id":"40-71-E-s17-7","route_short_name":"SEV 71 (AVG)","route_long_name":""},{"route_id":"40-E-E-s17-1","route_short_name":"SEV (DB AG)","route_long_name":""},{"route_id":"40-E-E-s17-2","route_short_name":"SEV (DB AG)","route_long_name":""},{"route_id":"40-E-E-s17-3","route_short_name":"SEV (DB AG)","route_long_name":""},{"route_id":"8-245-C-s17-2","route_short_name":"245 (RVS)","route_long_name":""},{"route_id":"8-262-C-s17-1","route_short_name":"262 (RVS)","route_long_name":""},{"route_id":"8-262-C-s17-2","route_short_name":"262 (RVS)","route_long_name":""}]}},{"type":"Feature","geometry":{"type":"Point","coordinates":[8.40112538663078,48.9917402348725]},"properties":{"stop_id":"de:08212:88:1:1","stop_name":"Karlsruhe Hauptbahnhof Süd","zone_id":"0100","stop_url":"","location_type":null,"parent_station":"","agency_key":"kvv","agency_name":"VBK GmbH","routes":[{"route_id":"24-44-E-s17-1","route_short_name":"44 (VBK)","route_long_name":""},{"route_id":"24-44-E-s17-3","route_short_name":"44 (VBK)","route_long_name":""},{"route_id":"24-44-E-s17-4","route_short_name":"44 (VBK)","route_long_name":""},{"route_id":"24-44-E-s17-5","route_short_name":"44 (VBK)","route_long_name":""},{"route_id":"24-44-E-s17-6","route_short_name":"44 (VBK)","route_long_name":""},{"route_id":"40-13-E-s17-2","route_short_name":"SEV S3 S31 S32 (AVG)","route_long_name":""},{"route_id":"40-13-E-s17-3","route_short_name":"SEV S3 S31 S32 (AVG)","route_long_name":""},{"route_id":"40-E-E-s17-1","route_short_name":"SEV (DB AG)","route_long_name":""},{"route_id":"40-E-E-s17-2","route_short_name":"SEV (DB AG)","route_long_name":""},{"route_id":"40-E-E-s17-3","route_short_name":"SEV (DB AG)","route_long_name":""}]}},{"type":"Feature","geometry":{"type":"Point","coordinates":[8.21484174613698,48.8608473568887]},"properties":{"stop_id":"de:08216:1844:2:7","stop_name":"Rastatt Bf","zone_id":"0361","stop_url":"","location_type":null,"parent_station":"Parent1844","agency_key":"kvv","agency_name":"VBK GmbH","routes":[{"route_id":"11-212-C-s17-3","route_short_name":"212 (BBL)","route_long_name":""},{"route_id":"12-231-E-s17-2","route_short_name":"231 (VERA)","route_long_name":""},{"route_id":"12-231-E-s17-3","route_short_name":"231 (VERA)","route_long_name":""},{"route_id":"12-231-E-s17-4","route_short_name":"231 (VERA)","route_long_name":""},{"route_id":"12-235-E-s17-2","route_short_name":"235 (VERA)","route_long_name":""},{"route_id":"30-222-C-s17-2","route_short_name":"222 (NVW)","route_long_name":""},{"route_id":"30-227-C-s17-1","route_short_name":"227 (NVW)","route_long_name":""},{"route_id":"40-71-E-s17-6","route_short_name":"SEV 71 (AVG)","route_long_name":""},{"route_id":"40-71-E-s17-7","route_short_name":"SEV 71 (AVG)","route_long_name":""},{"route_id":"40-E-E-s17-1","route_short_name":"SEV (DB AG)","route_long_name":""},{"route_id":"40-E-E-s17-2","route_short_name":"SEV (DB AG)","route_long_name":""},{"route_id":"40-E-E-s17-3","route_short_name":"SEV (DB AG)","route_long_name":""},{"route_id":"8-241-C-s17-1","route_short_name":"241 (RVS)","route_long_name":""}]}}]}